{
  "task_name": "Best Sim2Sim & Sim2Real Controller",
  "task_slug": "best_s2s_s2r",
  "version": "v2.0",
  "created": "2026-04-14",
  "status": "active",

  "goal": "构建 SOTA 级别的通用 sim2sim & sim2real 人形机器人运控部署工具",

  "project_context": {
    "robot": "Unitree G1 29DoF",
    "framework": "独立新项目 (universal_humanoid_controller)",
    "architecture": "Python + onnxruntime + Unitree SDK2 DDS",
    "environments": ["conda (开发/真机)", "Docker (隔离/CI)"],
    "code_sources": {
      "asap_sim2real": {
        "path": "/home/qiulm/sources/ASAP/sim2real",
        "usage": "复制核心模块并重构，不直接依赖"
      },
      "motion_tracking_controller": {
        "path": "/home/qiulm/sources/motion_tracking_controller",
        "usage": "仅参考 BeyondMimic 观测拼接逻辑，不复用框架"
      }
    },
    "model_sources": ["本地 ONNX 文件", "WandB run path 自动下载"]
  },

  "state_machine": {
    "states": ["PASSIVE", "BASE_ACTIVE", "TASK_ACTIVE", "E_STOP"],
    "transitions": [
      {"from": "PASSIVE", "to": "BASE_ACTIVE", "trigger": "[i] init interpolation"},
      {"from": "BASE_ACTIVE", "to": "TASK_ACTIVE", "trigger": "[]] activate task", "guard": "base_stable"},
      {"from": "TASK_ACTIVE", "to": "BASE_ACTIVE", "trigger": "[[] switch back / auto-return / fault"},
      {"from": "*", "to": "E_STOP", "trigger": "[o] emergency stop"},
      {"from": "E_STOP", "to": "PASSIVE", "trigger": "[i] manual reset"}
    ]
  },

  "milestones": [
    {
      "id": "M0",
      "name": "项目基建与环境配置",
      "scope": "基础设施",
      "status": "completed",
      "acceptance": [
        "独立项目仓库 + 标准目录结构",
        "conda environment.yml + install.sh 一键安装",
        "Dockerfile + docker_run.sh 一键启动",
        "基础包结构可 import",
        "配置加载框架可用"
      ]
    },
    {
      "id": "M1",
      "name": "核心框架 + ASAP Locomotion 基线",
      "scope": "sim2sim (MuJoCo)",
      "status": "completed",
      "acceptance": [
        "ASAP loco 控制机器人站立/行走",
        "单终端启动 sim2sim",
        "键盘控制 (i/]/o)",
        "模型支持本地路径和 WandB",
        "自动化测试 PASS"
      ]
    },
    {
      "id": "M1.5",
      "name": "ASAP Mimic 切换 + 操作流程打磨",
      "scope": "sim2sim loco↔ASAP mimic",
      "status": "completed",
      "completed_at": "2026-04-15",
      "code_repo": "universal_humanoid_controller",
      "acceptance": [
        "AsapMimicPolicy 加载 mimic ONNX 并执行",
        "loco↔mimic 切换与多技能选择 (; / ')",
        "与 ASAP 行为对齐（步进/插值/gap/start_upper_dof_pos）",
        "selftest 全量 PASS",
        "人工验收通过"
      ]
    },
    {
      "id": "M2",
      "name": "BeyondMimic 适配 + 策略切换",
      "scope": "sim2sim 多策略",
      "status": "completed",
      "completed_at": "2026-04-15",
      "code_repo": "universal_humanoid_controller",
      "acceptance": [
        "BeyondMimicPolicy 加载 ONNX + metadata 自描述",
        "JointMapper 处理 BeyondMimic L-R 交替序",
        "上肢插值目标坐标系正确（两端均 remap 到机器人序后相减）",
        "base_lin_vel 机体系转换与 IsaacLab 训练对齐",
        "motion_length_s 从 WandB motion artifact 正确解析（225.68s）",
        "phase 计算正确，phase_complete 自动返回",
        "selftest 76/76 PASS（插值阶段 + 30%片段 + 全量 phase）"
      ],
      "lessons_learned": [
        "关节顺序是新网络适配第一优先级：default_angles 和 ref_joint_pos 必须在同序下相减",
        "MuJoCo qvel[0:3] 是世界系，IsaacLab base_lin_vel 是机体系，需 quat_rotate_inverse 转换",
        "motion_length_s 必须从 WandB motion artifact(.npz) 读取，不能用训练 episode 超时长",
        "分段测试：插值验证 ≤5s，稳定性 ≥30%，phase/终止条件必须 100%"
      ]
    },
    {
      "id": "M3",
      "name": "Sim2Real + 安全 + 多输入",
      "scope": "真机部署",
      "status": "planned",
      "plan_doc": "m3_sim2real.md",
      "sub_phases": [
        "M3.0 环境准备（SDK 安装 + g1_29dof_real.yaml + check_real_env.py）",
        "M3.1 UnitreeBackend（DDS + FK + IMU 线速度估计）",
        "M3.2 安全体系增强（速度/姿态/心跳/真机 E_STOP 阻尼制动）",
        "M3.3 Xbox 手柄（与键盘语义等价）",
        "M3.4 Sim2Real Profile + PolicyRunner backend 分发",
        "M3.5 selftest_real.py(mock) + 真机人工验收"
      ],
      "acceptance": [
        "UnitreeBackend 接口与 MujocoBackend 完全兼容",
        "selftest_real.py mock 模式全 PASS（通信超时/关节限幅/IMU 异常）",
        "G1 真机 PASSIVE→BASE_ACTIVE 站立稳定 ≥5s",
        "G1 真机 loco 行走有速度响应",
        "G1 真机 loco↔BeyondMimic 切换 5 次不摔倒",
        "断网 100ms → 自动 E_STOP",
        "Xbox 手柄 START/B/X/BACK/摇杆全功能验证"
      ],
      "key_risks": [
        "base_lin_vel 真机 IMU 积分漂移 → 先接 loco（不依赖线速度），BeyondMimic 后调优",
        "真机 PD gains 需重新调参 → 保守系数 0.7 开始，悬空验证后再落地"
      ]
    },
    {
      "id": "M4",
      "name": "多策略在线切换 + 通用底座",
      "scope": "sim2sim 策略生态",
      "status": "completed",
      "status_note": "带条件验收通过（2026-04-17）；M4.3b 已延后至独立里程碑",
      "acceptance_mode": "conditional",
      "acceptance_conditions": [
        "策略切换验收口径为「底座接受上肢目标」+ 线性插值，非以 BFM 全身目标替代上肢插值",
        "RECOVERING 覆盖 TASK→BASE；在线 TASK→TASK 与 RECOVERING 对齐列入 M4.3b（deferred）",
        "急停仅按键 o；高度类异常不自动 E_STOP（项目级约束）",
        "躺倒启动：base_activate.sequence（先起身 goal 再 T-pose），阶段切换以时间/可选倾斜为主，sim2real 启动不依赖躯干高度",
        "「从躺倒自主恢复站立」以机制 + selftest + 约定 sim 流程验收，非全场景形式化自动化证明"
      ],
      "code_repo": "universal_humanoid_controller",
      "sub_phases": [
        "M4.1 多策略在线切换 Plan A（透明中转，~15行）",
        "M4.2 通用底座选型：BFM-Zero 选定 + BFMZeroPolicy 实现",
        "M4.3 通用底座集成：RECOVERING + 上肢目标切换 + BFM 恢复与 base_activate 序列",
        "M4.4 OmniXtreme 高动态策略接入"
      ],
      "sub_phase_status": {
        "M4.1": {
          "status": "completed",
          "completed_at": "2026-04",
          "plan_doc": "m4_multi_policy_switch.md",
          "implementation": "PolicyRunner._pending_task_switch_idx; keys ;/' in TASK_ACTIVE"
        },
        "M4.2": {
          "status": "completed",
          "date": "2026-04-16",
          "decision": "BFM-Zero (LeCAR-Lab, ICLR 2026)",
          "deliverables": [
            "uhc/policies/bfm_zero.py",
            "config/policies/bfm_zero.yaml",
            "config/profiles/sim2sim_bfm_zero.yaml",
            "scripts/verify_bfm_zero.py",
            "PolicyRunner._create_base_policy() dynamic loading"
          ],
          "report": "research/m4_2_bfm_zero_vs_host.md"
        },
        "M4.3": {
          "status": "completed",
          "completed_at": "2026-04-17",
          "notes": "RECOVERING；recovery latent；base_activate.sequence；插值 skill；M4.3b 不纳入"
        },
        "M4.4": {
          "status": "completed",
          "completed_at": "2026-04-16",
          "research": "research/omnixrtreme_uhc_adaptation.md"
        }
      },
      "key_candidates": {
        "universal_base": {
          "host": "单一recovery策略，行为固定",
          "bfm_zero": "可prompt行为基础模型，goal-reaching/tracking/reward，checkpoint+sim2sim+sim2real已开源",
          "decision": "已选定 BFM-Zero (2026-04-16)"
        }
      },
      "acceptance": [
        "TASK_ACTIVE 下 ;/' 切换到另一策略不摔倒",
        "底座能从躺倒自主恢复站立",
        "策略切换时底座接受上肢目标（当前阶段验收口径）",
        "OmniXtreme 高动态动作 sim2sim 稳定执行"
      ],
      "acceptance_progress": [
        "M4 闭合（带条件）：见 acceptance_mode 与 acceptance_conditions",
        "M4.1：已完成；多 task profile 连续切换建议仍作发布前 smoke",
        "M4.2：BFM-Zero 集成 + 插值修复 + skill（uhc-interpolation-debugging / uhc-policy-adaptation）",
        "M4.3：RECOVERING；确定性 recovery latent（tracking_tpose_step0）；base_activate.sequence 躺倒启动→起身→T-pose（时间/可选倾斜，不依赖启动高度）",
        "M4.3b：deferred（M5 后择机）；见 id=M4.3b",
        "M4.4：sim2sim 已验收（含 skip_position_clip）",
        "自动化：UHC scripts/selftest.py 全量通过（含状态机、M4.3 recovery stub、BFM base_activate 序列等）"
      ]
    },
    {
      "id": "M4.3b",
      "name": "在线 TASK→TASK 与 RECOVERING 路径对齐（可选）",
      "scope": "sim2sim PolicyRunner（; / ' 在线换技能）",
      "status": "deferred",
      "status_note": "当前跳过；M5 完成后再决定是否捡起",
      "code_repo": "universal_humanoid_controller",
      "problem": "RECOVERING 仅在 TASK→BASE 且非 pending 在线切换时触发；TASK_ACTIVE 下在线切到另一 task 仍走旧中转，不进入 RECOVERING。",
      "acceptance_if_resumed": [
        "在线 TASK→TASK 与 TASK→BASE 的恢复语义一致或可配置",
        "不破坏现有 M4.1 透明中转与上肢插值稳定性",
        "selftest 增补或专项脚本覆盖该路径"
      ],
      "reminder_after_milestone": "M5",
      "reminder_prompt": "询问维护者是否恢复开发 M4.3b"
    },
    {
      "id": "M5",
      "name": "通用追踪器 + 参考动作流式输入",
      "scope": "开放式策略架构",
      "status": "planned",
      "sub_phases": [
        "M5.1 MotionProvider 抽象层（FileProvider + StreamProvider）",
        "M5.2 OpenTrack 适配（优先，generalist v1 权重直接可用 + DAgger 复用 ASAP 专家）",
        "M5.3 BFM-Zero Tracker 模式（LeCAR-Lab/BFM-Zero）",
        "M5.4 SONIC/GR00T-WBC 适配（主要增量 = Planner + VR，对接 M6）",
        "M5.5 Kinematic Planner（SONIC）"
      ],
      "selection_rationale": "OpenTrack先于SONIC：ONNX导出路径成熟、权重直接可用、DAgger范式可复用本机16个ASAP专家策略、Pico协议(mj_retargeting)已就绪留给SONIC+M6",
      "acceptance": [
        "MotionProvider 接口：FileProvider + StreamProvider",
        "OpenTrack sim2sim LAFAN1 generalist 跟踪",
        "BFM-Zero tracking_inference 接入 UHC",
        "SONIC sim2sim LAFAN1 多动作跟踪"
      ]
    },
    {
      "id": "M6",
      "name": "遥操作（Teleoperation）",
      "scope": "实时人类输入设备",
      "status": "planned",
      "sub_phases": [
        "M6.1 Pico VR 接入（ZMQ，参考SONIC协议）",
        "M6.2 Retarget Pipeline（人体骨架 → G1）",
        "M6.3 MoCap 接入"
      ],
      "acceptance": [
        "Pico VR 手臂移动 → 机器人实时跟随（sim2sim）",
        "端到端延迟 < 50ms"
      ]
    },
    {
      "id": "M7",
      "name": "高层自主性（Planner / VLM / VLA）",
      "scope": "AI驱动行为",
      "status": "planned",
      "sub_phases": [
        "M7.1 Text-to-Motion（Kimodo等）",
        "M7.2 VLM/VLA 行为规划",
        "M7.3 感知-规划-控制闭环"
      ],
      "acceptance": [
        "自然语言 → 机器人动作（sim2sim）",
        "视觉 + 语言 → 行为序列 → 执行"
      ]
    }
  ],

  "key_decisions": [
    {
      "decision": "推倒重来，独立新项目",
      "rationale": "不与 ASAP/BeyondMimic 仓库耦合；从 ASAP 复制核心代码并重构",
      "date": "2026-04-14"
    },
    {
      "decision": "不复用 motion_tracking_controller Docker",
      "rationale": "围绕 ros2_control 构建，Python 方案不需要；重新写轻量 Dockerfile",
      "date": "2026-04-14"
    },
    {
      "decision": "conda + Docker 双轨环境",
      "rationale": "conda 用于开发/真机；Docker 用于隔离/CI/跨机器协作",
      "date": "2026-04-14"
    }
  ]
}
